ynot/__init__.py
ynot/constants.py
ynot/pathresolver.py
ynot/templateresolver.py
ynot/ynot.py
ynot/data/documentation_trafo.yaml
ynot/data/trafoschema.yaml
ynot-0.2.18.data/scripts/ynot
ynot-0.2.18.dist-info/DESCRIPTION.rst
ynot-0.2.18.dist-info/METADATA
ynot-0.2.18.dist-info/RECORD
ynot-0.2.18.dist-info/WHEEL
ynot-0.2.18.dist-info/metadata.json
ynot-0.2.18.dist-info/top_level.txt
