Metadata-Version: 2.0
Name: ynot
Version: 0.2.18
Summary: Yaml-based No-xml Transformation
Home-page: https://github.com/ynot/ynot
Author: Jakob Stemberger
Author-email: yaccob@gmx.net
License: Apache 2.0
Download-URL: https://github.com/yaccob/ynot/archive/0.2.18.tar.gz
Keywords: yaml,json,transform,xslt,jsonpath,json-path,dump,convert,validate,schema
Platform: UNKNOWN
Classifier: Programming Language :: Python :: 2.7
Requires-Dist: PyYaml
Requires-Dist: jsonpath-ng
Requires-Dist: jsonschema
